featureguards/__init__.py
featureguards/common.py
featureguards/evaluate.py
featureguards/feature_flags.py
featureguards/feature_toggles.py
featureguards/test_evaluate.py
featureguards/test_feature_flags.py
featureguards/proto/__init__.py
featureguards/proto/auth/__init__.py
featureguards/proto/auth/auth_pb2.py
featureguards/proto/auth/auth_pb2_grpc.py
featureguards/proto/shared/__init__.py
featureguards/proto/shared/feature_toggle_pb2.py
featureguards/proto/shared/user_pb2.py
featureguards/proto/toggles/__init__.py
featureguards/proto/toggles/toggles_pb2.py
featureguards/proto/toggles/toggles_pb2_grpc.py
featureguards/rpc/__init__.py
featureguards/rpc/client.py
featureguards-0.1.5.dist-info/LICENSE
featureguards-0.1.5.dist-info/METADATA
featureguards-0.1.5.dist-info/WHEEL
featureguards-0.1.5.dist-info/top_level.txt
featureguards-0.1.5.dist-info/RECORD
