Metadata-Version: 2.1
Name: featureguards
Version: 0.1.5
Summary: Official Python SDK for FeatureGuards
Home-page: https://github.com/featureguards/featureguards-python
Author: FeatureGuards
Author-email: eng@featureguards.com
License: MIT
License-File: LICENSE
Requires-Dist: grpcio
Requires-Dist: grpcio-status
Requires-Dist: xxhash
Requires-Dist: protobuf
